academic_contacts/__init__.py
academic_contacts/about.py
academic_contacts/desktop.py
academic_contacts/program.py
academic_contacts/icons/elsevier.png
academic_contacts/icons/logo.png
academic_contacts/icons/mdpi.png
academic_contacts/modules/__init__.py
academic_contacts/modules/configure.py
academic_contacts/modules/wabout.py
academic_contacts-0.1.5.dist-info/licenses/LICENSE
academic_contacts-0.1.5.dist-info/METADATA
academic_contacts-0.1.5.dist-info/WHEEL
academic_contacts-0.1.5.dist-info/entry_points.txt
academic_contacts-0.1.5.dist-info/top_level.txt
academic_contacts-0.1.5.dist-info/RECORD
